compare50/__init__.py
compare50/__main__.py
compare50/_api.py
compare50/_data.py
compare50/passes.py
compare50/preprocessors.py
compare50/_renderer/__init__.py
compare50/_renderer/_renderer.py
compare50/_renderer/static/bootstrap.min.css
compare50/_renderer/static/d3-scale-chromatic.v1.min.js
compare50/_renderer/static/d3-simple-slider.js
compare50/_renderer/static/d3.v4.min.js
compare50/_renderer/static/fonts.css
compare50/_renderer/static/index.css
compare50/_renderer/static/index.js
compare50/_renderer/static/match.css
compare50/_renderer/static/match.js
compare50/_renderer/static/split.min.js
compare50/_renderer/templates/index.html
compare50/_renderer/templates/match.html
compare50/_renderer/templates/match_page.html
compare50/comparators/__init__.py
compare50/comparators/_misspellings.py
compare50/comparators/_winnowing.py
compare50/comparators/english_dictionary.txt
compare50-1.2.12.data/scripts/compare50
compare50-1.2.12.dist-info/licenses/LICENSE
compare50-1.2.12.dist-info/METADATA
compare50-1.2.12.dist-info/WHEEL
compare50-1.2.12.dist-info/top_level.txt
compare50-1.2.12.dist-info/RECORD
