Metadata-Version: 2.4
Name: compare50
Version: 1.2.12
Summary: This is compare50, with which you can compare files for similarities.
Home-page: https://github.com/cs50/compare50
Author: CS50
Author-email: sysadmins@cs50.harvard.edu
License: GPLv3
Keywords: compare,compare50
Classifier: Intended Audience :: Education
Classifier: Programming Language :: Python :: 3.8
Classifier: Topic :: Education
Classifier: Topic :: Utilities
Requires-Python: >=3.8
License-File: LICENSE
Requires-Dist: attrs<21,>=18
Requires-Dist: intervaltree<4,>=3
Requires-Dist: lib50<4,>=2
Requires-Dist: numpy<2,>=1.15
Requires-Dist: pygments<3,>=2.2
Requires-Dist: jinja2<4,>=3
Requires-Dist: termcolor<2,>=1.1.0
Requires-Dist: tqdm<5,>=4.32
Requires-Dist: importlib
Provides-Extra: develop
Requires-Dist: sphinx; extra == "develop"
Requires-Dist: sphinx_rtd_theme; extra == "develop"
Requires-Dist: sphinx-autobuild; extra == "develop"
Requires-Dist: line_profiler; extra == "develop"
Dynamic: author
Dynamic: author-email
Dynamic: classifier
Dynamic: description
Dynamic: home-page
Dynamic: keywords
Dynamic: license
Dynamic: license-file
Dynamic: provides-extra
Dynamic: requires-dist
Dynamic: requires-python
Dynamic: summary
